dash_pivottable/PivotTable.py
dash_pivottable/__init__.py
dash_pivottable/_imports_.py
dash_pivottable/dash_pivottable.dev.js
dash_pivottable/dash_pivottable.min.js
dash_pivottable/metadata.json
dash_pivottable/package.json
dash_pivottable-0.0.2.dist-info/LICENSE
dash_pivottable-0.0.2.dist-info/METADATA
dash_pivottable-0.0.2.dist-info/WHEEL
dash_pivottable-0.0.2.dist-info/top_level.txt
dash_pivottable-0.0.2.dist-info/RECORD
