Metadata-Version: 1.0
Name: dash_pivottable
Version: 0.0.2
Summary: Implementation of react-pivottable in Dash (Python)
Home-page: UNKNOWN
Author: Xing Han Lu <xinghan@plotly.com>
Author-email: UNKNOWN
License: MIT
Platform: UNKNOWN
